langchain_galaxia_retriever/__init__.py
langchain_galaxia_retriever/retriever.py
langchain_galaxia_retriever-0.1.2.dist-info/LICENSE
langchain_galaxia_retriever-0.1.2.dist-info/METADATA
langchain_galaxia_retriever-0.1.2.dist-info/WHEEL
langchain_galaxia_retriever-0.1.2.dist-info/RECORD
