Metadata-Version: 2.1
Name: langchain-galaxia-retriever
Version: 0.1.2
Summary: langchain galaxia integration
License: MIT
Author: Robert Rozanski
Requires-Python: >=3.10,<4.0
Classifier: License :: OSI Approved :: MIT License
Classifier: Programming Language :: Python :: 3
Classifier: Programming Language :: Python :: 3.10
Classifier: Programming Language :: Python :: 3.11
Classifier: Programming Language :: Python :: 3.12
Requires-Dist: langchain-core (>=0.3.21,<0.4.0)
